setup.cfg
setup.py
lmi/__init__.py
lmi/scripts/__init__.py
lmi/scripts/service/__init__.py
lmi/scripts/service/cmd.py
openlmi_scripts_service.egg-info/PKG-INFO
openlmi_scripts_service.egg-info/SOURCES.txt
openlmi_scripts_service.egg-info/dependency_links.txt
openlmi_scripts_service.egg-info/entry_points.txt
openlmi_scripts_service.egg-info/namespace_packages.txt
openlmi_scripts_service.egg-info/requires.txt
openlmi_scripts_service.egg-info/top_level.txt