Metadata-Version: 1.1
Name: openlmi-scripts-service
Version: 0.1.1
Summary: LMI command for system service administration.
Home-page: https://github.com/openlmi/openlmi-scripts
Author: Michal Minar
Author-email: miminar@redhat.com
License: BSD
Download-URL: https://github.com/openlmi/openlmi-scripts/tarball/master
Platform: Any
Classifier: License :: OSI Approved :: BSD License
Classifier: Operating System :: POSIX :: Linux
Classifier: Topic :: System :: Systems Administration
Classifier: Programming Language :: Python
Classifier: Programming Language :: Python :: 2
Classifier: Programming Language :: Python :: 2.7
Classifier: Intended Audience :: Developers
Classifier: Environment :: Console
